jobs/badpyjob.py
jobs/printer.py
jobs/pyjob.py
skedulord/__init__.py
skedulord/__main__.py
skedulord/api.py
skedulord/auth.py
skedulord/common.py
skedulord/cron.py
skedulord/dashboard.py
skedulord/db.py
skedulord/demo_seed.py
skedulord/job.py
skedulord/templating.py
skedulord/static/favicon.png
skedulord/static/index.html
skedulord/static/assets/index-BIcQ2FMP.js
skedulord/static/assets/index-vlFSFsvP.css
skedulord/templates/index.html
skedulord/templates/job.html
skedulord/templates/layout.html
skedulord/templates/macros.html
skedulord-3.0.6.dist-info/licenses/LICENSE
tests/test_add_command.py
tests/test_api_security.py
tests/test_cron_parsing.py
tests/test_export.py
tests/test_happy_path.py
tests/test_init_command.py
tests/test_unhappy_path.py
skedulord-3.0.6.dist-info/METADATA
skedulord-3.0.6.dist-info/WHEEL
skedulord-3.0.6.dist-info/entry_points.txt
skedulord-3.0.6.dist-info/top_level.txt
skedulord-3.0.6.dist-info/RECORD
