Metadata-Version: 2.4
Name: skedulord
Version: 3.0.6
Summary: A tool that automates scheduling and logging of jobs.
Author: Vincent D. Warmerdam
License: MIT
Requires-Python: >=3.9
License-File: LICENSE
Requires-Dist: PyYAML>=5.1.1
Requires-Dist: clumper>=0.2.8
Requires-Dist: fastapi>=0.110.0
Requires-Dist: jinja2>=3.1.0
Requires-Dist: python-crontab>=2.5.1
Requires-Dist: rich>=9.10.0
Requires-Dist: typer>=0.3.2
Requires-Dist: uvicorn>=0.29.0
Provides-Extra: dev
Requires-Dist: pytest; extra == "dev"
Requires-Dist: pytest-cov; extra == "dev"
Requires-Dist: httpx; extra == "dev"
Requires-Dist: mkdocs-material>=6.2.8; extra == "dev"
Requires-Dist: ruff>=0.5.0; extra == "dev"
Dynamic: license-file
